devmem/__init__.py
devmem-0.1.0.dist-info/LICENSE
devmem-0.1.0.dist-info/METADATA
devmem-0.1.0.dist-info/WHEEL
devmem-0.1.0.dist-info/entry_points.txt
devmem-0.1.0.dist-info/top_level.txt
devmem-0.1.0.dist-info/RECORD
