Metadata-Version: 2.1
Name: devmem
Version: 0.1.0
Summary: Python devmem clone
Home-page: https://github.com/kylemanna/pydevmem
Author: Kyle Manna
Author-email: kyle@kylemanna.com
License: MIT
Platform: UNKNOWN
Classifier: License :: OSI Approved :: MIT License
Classifier: Programming Language :: Python :: 3
Classifier: Programming Language :: Python :: 3.8
